redacted/__init__.py
redacted/__main__.py
redacted/dictionary.py
redacted/redactor.py
redacted/tag.py
redacted_py-1.0.10.dist-info/licenses/LICENSE
redacted_py-1.0.10.dist-info/METADATA
redacted_py-1.0.10.dist-info/WHEEL
redacted_py-1.0.10.dist-info/entry_points.txt
redacted_py-1.0.10.dist-info/top_level.txt
redacted_py-1.0.10.dist-info/RECORD
