Metadata-Version: 2.4
Name: redacted-py
Version: 1.0.10
Summary: Redacting classified documents
Author-email: Cyril Dever <cdever@pep-s.com>
License: Copyright (c) 2024 Cyril Dever
Project-URL: Homepage, https://github.com/cyrildever/redacted
Keywords: data,obfuscation,data masking,redacted,classified
Classifier: Programming Language :: Python :: 3
Classifier: License :: OSI Approved :: MIT License
Classifier: Operating System :: OS Independent
Requires-Python: >=3.10.2
License-File: LICENSE
Requires-Dist: feistel-py>=1.0.0
Dynamic: license-file
